psignifit/__init__.py
psignifit/_confidence.py
psignifit/_configuration.py
psignifit/_parameter.py
psignifit/_posterior.py
psignifit/_priors.py
psignifit/_result.py
psignifit/_typing.py
psignifit/_utils.py
psignifit/psignifit.py
psignifit/psigniplot.py
psignifit/sigmoids.py
psignifit/tools.py
psignifit-4.3.dist-info/METADATA
psignifit-4.3.dist-info/WHEEL
psignifit-4.3.dist-info/top_level.txt
psignifit-4.3.dist-info/RECORD
