Metadata-Version: 2.2
Name: psignifit
Version: 4.3
Summary: Toolbox for Bayesian psychometric function estimation
Author: psignifit contributors, www.wichmann-lab.org
Maintainer: psignifit contributors, www.wichmann-lab.org
License: This file is part of psignifit
Project-URL: Homepage, http://www.wichmann-lab.org/
Project-URL: Documentation, https://psignifit.readthedocs.io/en/latest/
Project-URL: Repository, https://github.com/wichmann-lab/python-psignifit.git
Project-URL: Issues, https://github.com/wichmann-lab/python-psignifit/issues
Keywords: psychometric,psychophysics,function,statistics
Classifier: Development Status :: 5 - Production/Stable
Classifier: Intended Audience :: Science/Research
Classifier: Topic :: Scientific/Engineering :: Information Analysis
Classifier: License :: OSI Approved :: GNU General Public License v3 (GPLv3)
Classifier: Programming Language :: Python :: 3
Classifier: Programming Language :: Python :: 3.10
Classifier: Programming Language :: Python :: 3.11
Classifier: Programming Language :: Python :: 3.12
Requires-Python: >=3.10
Requires-Dist: scipy
Requires-Dist: matplotlib
Provides-Extra: tests
Requires-Dist: pytest; extra == "tests"
Requires-Dist: pytest-cov; extra == "tests"
Requires-Dist: flake8; extra == "tests"
Provides-Extra: docs
Requires-Dist: sphinx; extra == "docs"
Requires-Dist: sphinx-gallery; extra == "docs"
Requires-Dist: sphinx_rtd_theme; extra == "docs"
Requires-Dist: matplotlib; extra == "docs"
Requires-Dist: jupyter-book==0.14; extra == "docs"
Requires-Dist: jupytext>=1.13.3; extra == "docs"
Requires-Dist: jupyterlab_myst; extra == "docs"
Requires-Dist: myst_nb; extra == "docs"
Requires-Dist: ipywidgets; extra == "docs"
Requires-Dist: sphinx-hoverxref; extra == "docs"
